extras/__init__.py
extras/divide.py
extras/multiply.py
paramchauhan-0.0.1.dist-info/DESCRIPTION.rst
paramchauhan-0.0.1.dist-info/METADATA
paramchauhan-0.0.1.dist-info/RECORD
paramchauhan-0.0.1.dist-info/WHEEL
paramchauhan-0.0.1.dist-info/metadata.json
paramchauhan-0.0.1.dist-info/top_level.txt
